[{"startdate": "2015-12-10", "enddate": "2015-12-14", "name": ["Days of Tango - 2015"], "city": "St. Petersburg", "url": "http://www.diastango.otango.ru/index.html", "country": "Russia", "extra_fsrurl": "http://www.festivalsero.com/days_of_tango__2015-6293", "emurl": "", "extra_fsrtyp": true, "fburl": ""}, {"startdate": "2015-12-11", "enddate": "2015-12-13", "name": ["The Day of Tango"], "city": "Austin, TX", "url": "http://www.dayoftango.org", "country": "United States", "extra_fsrurl": "http://www.festivalsero.com/the_day_of_tango-6084", "emurl": "", "extra_fsrtyp": true, "fburl": ""}, {"startdate": "2015-12-26", "enddate": "2016-01-03", "name": ["TangoTrain Amsterdam"], "city": "Amsterdam", "url": "http://www.tangotrain.com/", "country": "Netherlands", "extra_fsrurl": "http://www.festivalsero.com/tangotrain_amsterdam-6067", "emurl": "", "extra_fsrtyp": true, "fburl": ""}, {"startdate": "2015-12-27", "enddate": "2016-01-03", "name": ["Dutch International Tangoweek"], "city": "Amsterdam", "url": "http://www.dutchtangoweek.nl", "country": "Netherlands", "extra_fsrurl": "http://www.festivalsero.com/dutch_international_tangoweek-5559", "emurl": "", "extra_fsrtyp": true, "fburl": ""}, {"startdate": "2015-12-27", "enddate": "2016-01-02", "name": ["International Taboe Tango Camp"], "city": "Austerlitz", "url": "http://tangoatelier.nl/UKindex.html", "country": "Netherlands", "extra_fsrurl": "http://www.festivalsero.com/international_taboe_tango_camp-5725", "emurl": "", "extra_fsrtyp": true, "fburl": ""}, {"startdate": "2015-12-31", "enddate": "2016-01-03", "name": ["Barcelona Tango Festival"], "city": "Barcelona", "url": "http://www.festivalbarcelonatango.com", "country": "Spain", "extra_fsrurl": "http://www.festivalsero.com/barcelona_tango_festival-5726", "emurl": "", "extra_fsrtyp": true, "fburl": ""}, {"startdate": "2015-12-31", "enddate": "2016-01-03", "name": ["Newcastle Salsa Congress"], "city": "Newcastle Upon Tyne", "url": "http://www.newcastlesalsacongress.co.uk/", "country": "United Kingdom", "extra_fsrurl": "http://www.festivalsero.com/newcastle_salsa_congress-5728", "emurl": "", "extra_fsrtyp": false, "fburl": ""}, {"startdate": "2015-12-31", "enddate": "2016-01-04", "name": ["San Diego Tango Festival"], "city": "San Diego, CA", "url": "http://www.sandiegotangofestival.com/", "country": "United States", "extra_fsrurl": "http://www.festivalsero.com/san_diego_tango_festival-5729", "emurl": "", "extra_fsrtyp": true, "fburl": ""}, {"startdate": "2015-12-31", "enddate": "2016-01-03", "name": ["II Tango Festival of Barcelona"], "city": "Barcelona", "url": "http://festivalbarcelonatango.com/", "country": "Spain", "extra_fsrurl": "http://www.festivalsero.com/ii_tango_festival_of_barcelona-6273", "emurl": "", "extra_fsrtyp": true, "fburl": ""}, {"startdate": "2015-12-31", "enddate": "2016-01-01", "name": ["New Year Tango Ball"], "city": "Sofia", "url": "http://bulgariatango.com/?page_id=364", "country": "Bulgaria", "extra_fsrurl": "http://www.festivalsero.com/new_year_tango_ball-6297", "emurl": "", "extra_fsrtyp": true, "fburl": ""}, {"startdate": "2016-01-01", "enddate": "2016-01-03", "name": ["Encuentro Milonguero: Noches de Invierno"], "city": "Reichenau an der Rax", "url": "http://www.nochesdeinvierno.com", "country": "Austria", "extra_fsrurl": "http://www.festivalsero.com/encuentro_milonguero_noches_de_invierno-5727", "emurl": "", "extra_fsrtyp": true, "fburl": ""}, {"startdate": "2016-01-01", "enddate": "2016-01-07", "name": ["Moscow Tango Holidays"], "city": "Moscow", "url": "http://mostangoholidays.com/en", "country": "Russia", "extra_fsrurl": "http://www.festivalsero.com/moscow_tango_holidays-6298", "emurl": "", "extra_fsrtyp": true, "fburl": ""}, {"startdate": "2016-01-08", "enddate": "2016-01-10", "name": ["Toronto Tango Marathon"], "city": "Toronto", "url": "http://www.torontotangomarathon.com/", "country": "Canada", "extra_fsrurl": "http://www.festivalsero.com/toronto_tango_marathon-6068", "emurl": "", "extra_fsrtyp": true, "fburl": ""}, {"startdate": "2016-01-29", "enddate": "2016-01-31", "name": ["Singapore International Latin Festival"], "city": "Singapore", "url": "http://www.siblf.sg/", "country": "Singapore", "extra_fsrurl": "http://www.festivalsero.com/singapore_international_latin_festival-5749", "emurl": "", "extra_fsrtyp": false, "fburl": ""}, {"startdate": "2016-02-04", "enddate": "2016-02-07", "name": ["TangoLovers Festival"], "city": "Athens", "url": "http://tangoloversfestival.gr/en/", "country": "Greece", "extra_fsrurl": "http://www.festivalsero.com/tangolovers_festival-6300", "emurl": "", "extra_fsrtyp": true, "fburl": ""}, {"startdate": "2016-02-05", "enddate": "2016-02-07", "name": ["Vinterfestival i \u00c3\u0085s"], "city": "\u00c3\u0096stersund", "url": "http://www.tangojamt.com/index.php?todo=festival", "country": "Sweden", "extra_fsrurl": "http://www.festivalsero.com/vinterfestival_i_as-5758", "emurl": "", "extra_fsrtyp": true, "fburl": ""}, {"startdate": "2016-02-05", "enddate": "2016-02-07", "name": ["Encuentro Tango y Bailes de Salon"], "city": "Alcoy", "url": "http://encuentroalcoy.marilufischer.com/", "country": "Spain", "extra_fsrurl": "http://www.festivalsero.com/encuentro_tango_y_bailes_de_salon-6168", "emurl": "", "extra_fsrtyp": true, "fburl": ""}, {"startdate": "2016-02-10", "enddate": "2016-02-15", "name": ["Portland ValenTango"], "city": "Portland, OR", "url": "http://valentango.us/", "country": "United States", "extra_fsrurl": "http://www.festivalsero.com/portland_valentango-5783", "emurl": "", "extra_fsrtyp": true, "fburl": ""}, {"startdate": "2016-02-12", "enddate": "2016-02-14", "name": ["International \"Amor\" Tango Festival Rosario"], "city": "Rosario", "url": "http://www.amortangofest.com/#!/-festival-2016/", "country": "Argentina", "extra_fsrurl": "http://www.festivalsero.com/international_amor_tango_festival_rosario-6252", "emurl": "", "extra_fsrtyp": true, "fburl": ""}, {"startdate": "2016-02-17", "enddate": "2016-02-21", "name": ["Workshop Milonga Sevilla"], "city": "Seville", "url": "http://www.workshopmilongasevilla.com/", "country": "Spain", "extra_fsrurl": "http://www.festivalsero.com/workshop_milonga_sevilla-6073", "emurl": "", "extra_fsrtyp": true, "fburl": ""}, {"startdate": "2016-02-26", "enddate": "2016-02-28", "name": ["Tango Fireworks"], "city": "New Delhi", "url": "http://www.delhimilonga.com/delhi-tango-festival", "country": "India", "extra_fsrurl": "http://www.festivalsero.com/tango_fireworks-5788", "emurl": "", "extra_fsrtyp": true, "fburl": ""}, {"startdate": "2016-03-04", "enddate": "2016-03-06", "name": ["Seattle Tango Marathon"], "city": "Seattle, WA", "url": "http://www.seattletangomarathon.com", "country": "United States", "extra_fsrurl": "http://www.festivalsero.com/seattle_tango_marathon-5842", "emurl": "", "extra_fsrtyp": true, "fburl": ""}, {"startdate": "2016-03-07", "enddate": "2016-03-13", "name": ["Canary Islands Tango Festival"], "city": "Las Palmas", "url": "http://www.canaryislandstangofestival.com/", "country": "Spain", "extra_fsrurl": "http://www.festivalsero.com/canary_islands_tango_festival-5801", "emurl": "", "extra_fsrtyp": true, "fburl": ""}, {"startdate": "2016-03-11", "enddate": "2016-03-13", "name": ["Summer Tango in Nelson"], "city": "Nelson", "url": "http://www.summertangoinnelson.co.nz/", "country": "New Zealand", "extra_fsrurl": "http://www.festivalsero.com/summer_tango_in_nelson-5799", "emurl": "", "extra_fsrtyp": true, "fburl": ""}, {"startdate": "2016-03-11", "enddate": "2016-03-13", "name": ["TangoBiathlon"], "city": "Munich", "url": "http://www.tangobiathlon.com/", "country": "Germany", "extra_fsrurl": "http://www.festivalsero.com/tangobiathlon-5818", "emurl": "", "extra_fsrtyp": true, "fburl": ""}, {"startdate": "2016-03-13", "enddate": "2016-03-19", "name": ["CITA - Congreso Internacional de Tango Argentino"], "city": "Buenos Aires", "url": "http://www.tangopal.com/cita.the.event", "country": "Argentina", "extra_fsrurl": "http://www.festivalsero.com/cita__congreso_internacional_de_tango_argentino-6078", "emurl": "", "extra_fsrtyp": true, "fburl": ""}, {"startdate": "2016-03-31", "enddate": "2016-04-03", "name": ["Calgary International Salsa Congress"], "city": "Calgary", "url": "http://calgarysalsacongress.com/", "country": "Canada", "extra_fsrurl": "http://www.festivalsero.com/calgary_international_salsa_congress-5858", "emurl": "", "extra_fsrtyp": false, "fburl": ""}, {"startdate": "2016-04-01", "enddate": "2016-04-03", "name": ["Montecatini Terme Tango  Festivalito"], "city": "Montecatini Terme", "url": "http://www.tangotuscany.com/montecatini-terme-tango-festivalito.html", "country": "Italy", "extra_fsrurl": "http://www.festivalsero.com/montecatini_terme_tango__festivalito-5899", "emurl": "", "extra_fsrtyp": true, "fburl": ""}, {"startdate": "2016-04-07", "enddate": "2016-04-10", "name": ["Tucson Tango Festival"], "city": "Tucson, AZ", "url": "http://tucsontangofestival.com", "country": "United States", "extra_fsrurl": "http://www.festivalsero.com/tucson_tango_festival-5872", "emurl": "", "extra_fsrtyp": true, "fburl": ""}, {"startdate": "2016-04-07", "enddate": "2016-04-10", "name": ["Aix en Provence Tango Festival"], "city": "Aix-en-Provence", "url": "http://AixTangoFestival.com", "country": "France", "extra_fsrurl": "http://www.festivalsero.com/aix_en_provence_tango_festival-5877", "emurl": "", "extra_fsrtyp": true, "fburl": ""}, {"startdate": "2016-04-14", "enddate": "2016-04-17", "name": ["Chicago Mini Tango Festival"], "city": "Chicago, IL", "url": "http://www.chicagotangofestival.com", "country": "United States", "extra_fsrurl": "http://www.festivalsero.com/chicago_mini_tango_festival-6081", "emurl": "", "extra_fsrtyp": true, "fburl": ""}, {"startdate": "2016-04-15", "enddate": "2016-04-17", "name": ["Encuentro de Tango Benidorm"], "city": "Benidorm", "url": "http://www.encuentrotangobenidorm.marilufischer.com/", "country": "Spain", "extra_fsrurl": "http://www.festivalsero.com/encuentro_de_tango_benidorm-6171", "emurl": "", "extra_fsrtyp": true, "fburl": ""}, {"startdate": "2016-04-15", "enddate": "2016-04-17", "name": ["III Festival Tangom\u00c3\u00a1gico"], "city": "Santander", "url": "http://www.magiadelbaile.es/iii-festival-tangomagico/", "country": "Spain", "extra_fsrurl": "http://www.festivalsero.com/iii_festival_tangomagico-6333", "emurl": "", "extra_fsrtyp": true, "fburl": ""}, {"startdate": "2016-04-21", "enddate": "2016-04-25", "name": ["Firenze Tango Festival"], "city": "Firenze", "url": "http://www.firenzetangofestival.com/", "country": "Italy", "extra_fsrurl": "http://www.festivalsero.com/firenze_tango_festival-5934", "emurl": "", "extra_fsrtyp": true, "fburl": ""}, {"startdate": "2016-04-22", "enddate": "2016-04-25", "name": ["Pescara Tango Festival"], "city": "Montesilvano", "url": "http://www.pescaratangofestival.it/", "country": "Italy", "extra_fsrurl": "http://www.festivalsero.com/pescara_tango_festival-5916", "emurl": "", "extra_fsrtyp": true, "fburl": ""}, {"startdate": "2016-04-22", "enddate": "2016-04-24", "name": ["ESO! Buffalo Tango Marathon"], "city": "Buffalo, NY", "url": "http://www.esobuffalo.com", "country": "United States", "extra_fsrurl": "http://www.festivalsero.com/eso_buffalo_tango_marathon-5920", "emurl": "", "extra_fsrtyp": true, "fburl": ""}, {"startdate": "2016-04-27", "enddate": "2016-05-01", "name": ["Benidorm Tango Festival"], "city": "Benidorm", "url": "http://www.benidormtangofestival.com/", "country": "Spain", "extra_fsrurl": "http://www.festivalsero.com/benidorm_tango_festival-6173", "emurl": "", "extra_fsrtyp": true, "fburl": ""}, {"startdate": "2016-04-29", "enddate": "2016-05-02", "name": ["Che London Tango Festival"], "city": "London", "url": "http://www.tanguito.co.uk/londontangofestival/", "country": "United Kingdom", "extra_fsrurl": "http://www.festivalsero.com/che_london_tango_festival-5935", "emurl": "", "extra_fsrtyp": true, "fburl": ""}, {"startdate": "2016-04-29", "enddate": "2016-05-01", "name": ["Arrabal - Tangofestival Potsdam"], "city": "Potsdam", "url": "http://www.tanguito.de/arrabal.html", "country": "Germany", "extra_fsrurl": "http://www.festivalsero.com/arrabal__tangofestival_potsdam-6174", "emurl": "", "extra_fsrtyp": true, "fburl": ""}, {"startdate": "2016-05-04", "enddate": "2016-05-08", "name": ["Tangoamadeus - Vienna Tango Festival"], "city": "Vienna", "url": "http://www.tangoamadeus.com/", "country": "Austria", "extra_fsrurl": "http://www.festivalsero.com/tangoamadeus__vienna_tango_festival-5953", "emurl": "", "extra_fsrtyp": true, "fburl": ""}, {"startdate": "2016-05-05", "enddate": "2016-05-08", "name": ["Festivalito Tango Primavera"], "city": "Zurich", "url": "http://www.festivalito.ch/", "country": "Switzerland", "extra_fsrurl": "http://www.festivalsero.com/festivalito_tango_primavera-6089", "emurl": "", "extra_fsrtyp": true, "fburl": ""}, {"startdate": "2016-05-06", "enddate": "2016-05-08", "name": ["Abrazos - Encuentro Milonguero"], "city": "Dartington", "url": "http://www.tangokombinat.de/uk_abrazos.htm", "country": "United Kingdom", "extra_fsrurl": "http://www.festivalsero.com/abrazos__encuentro_milonguero-5955", "emurl": "", "extra_fsrtyp": true, "fburl": ""}, {"startdate": "2016-05-10", "enddate": "2016-05-16", "name": ["Embrace"], "city": "Berlin", "url": "http://embrace-berlin.de/", "country": "Germany", "extra_fsrurl": "http://www.festivalsero.com/embrace-6177", "emurl": "", "extra_fsrtyp": true, "fburl": ""}, {"startdate": "2016-05-13", "enddate": "2016-05-15", "name": ["Antwerpen Tango Festival"], "city": "Antwerp", "url": "http://antwerpentangofestival.com/", "country": "Belgium", "extra_fsrurl": "http://www.festivalsero.com/antwerpen_tango_festival-6204", "emurl": "", "extra_fsrtyp": true, "fburl": ""}, {"startdate": "2016-05-14", "enddate": "2016-05-16", "name": ["Pfingsten Tango Luzern"], "city": "Luzern", "url": "http://www.elsocial.ch/Pages/Tango_festival_luzern.htm", "country": "Switzerland", "extra_fsrurl": "http://www.festivalsero.com/pfingsten_tango_luzern-5296", "emurl": "", "extra_fsrtyp": true, "fburl": ""}, {"startdate": "2016-05-20", "enddate": "2016-05-22", "name": ["Milonguero Dias de Juventud III"], "city": "Ljubljana", "url": "http://www.tango.si/napovedujemo/item/66-dias-de-juventud", "country": "Slovenia", "extra_fsrurl": "http://www.festivalsero.com/milonguero_dias_de_juventud_iii-5655", "emurl": "", "extra_fsrtyp": true, "fburl": ""}, {"startdate": "2016-05-27", "enddate": "2016-05-30", "name": ["Edinburgh International Tango Festival"], "city": "Edinburgh", "url": "http://eitf.org.uk/", "country": "United Kingdom", "extra_fsrurl": "http://www.festivalsero.com/edinburgh_international_tango_festival-5997", "emurl": "", "extra_fsrtyp": true, "fburl": ""}, {"startdate": "2016-05-27", "enddate": "2016-05-29", "name": ["Louisville Tango Festival"], "city": "Louisville, KY", "url": "http://www.louisvilletangofestival.com", "country": "United States", "extra_fsrurl": "http://www.festivalsero.com/louisville_tango_festival-6310", "emurl": "", "extra_fsrtyp": true, "fburl": ""}, {"startdate": "2016-05-28", "enddate": "2016-05-29", "name": ["Strasbourg Milonga"], "city": "Strasbourg", "url": "http://www.strastango.org/festival/", "country": "France", "extra_fsrurl": "http://www.festivalsero.com/strasbourg_milonga-5669", "emurl": "", "extra_fsrtyp": true, "fburl": ""}, {"startdate": "2016-05-28", "enddate": "2016-05-30", "name": ["England International Tango Festival"], "city": "Brighton", "url": "http://englandinternationaltangofestival.com/index.html", "country": "United Kingdom", "extra_fsrurl": "http://www.festivalsero.com/england_international_tango_festival-6091", "emurl": "", "extra_fsrtyp": true, "fburl": ""}]